{
  "n": 3,
  "year": "1993",
  "flag": "🇱🇰",
  "loc": "International Centre · Colombo, Sri Lanka",
  "title": "Buddhist Women in Modern Society",
  "subtitle": "",
  "dates": "1993",
  "host": "Sakyadhita International",
  "about": "The 3rd conference gathered in Colombo, Sri Lanka, examining the role of Buddhist women in modern society — and laying groundwork for the restoration of the bhikkhuni order in the Theravada tradition.",
  "photos": [
    {
      "f": "/uploads/conf03-colombo.jpg",
      "caption": "Colombo, 1993"
    }
  ]
}